{
  "$schema": "https://developer.microsoft.com/json-schemas/fabric/item/report/definition/visualContainer/2.1.0/schema.json",
  "name": "c1a082e1bf7924c555e3",
  "position": {
    "x": 182,
    "y": 0,
    "z": 1000,
    "height": 59,
    "width": 894,
    "tabOrder": 8000
  },
  "visual": {
    "visualType": "textbox",
    "objects": {
      "general": [
        {
          "properties": {
            "paragraphs": [
              {
                "textRuns": [
                  {
                    "value": "Balanza Turística",
                    "textStyle": {
                      "fontWeight": "bold",
                      "fontSize": "20pt",
                      "color": "#ffffff"
                    }
                  }
                ],
                "indent": 1
              },
              {
                "textRuns": [
                  {
                    "value": ""
                  }
                ]
              }
            ]
          }
        }
      ]
    }
  }
}